lvmieb/__init__.py
lvmieb/__main__.py
lvmieb/actor/__init__.py
lvmieb/actor/actor.py
lvmieb/actor/commands/__init__.py
lvmieb/actor/commands/depth.py
lvmieb/actor/commands/hartmann.py
lvmieb/actor/commands/shutter.py
lvmieb/actor/commands/transducer.py
lvmieb/actor/commands/wago.py
lvmieb/controller/__init__.py
lvmieb/controller/controller.py
lvmieb/controller/depth.py
lvmieb/controller/maskbits.py
lvmieb/controller/motor.py
lvmieb/controller/pressure.py
lvmieb/controller/wago.py
lvmieb/etc/lvmieb.yml
lvmieb/etc/schema.json
lvmieb/exceptions.py
sdss_lvmieb-0.5.3.dist-info/LICENSE.md
sdss_lvmieb-0.5.3.dist-info/METADATA
sdss_lvmieb-0.5.3.dist-info/WHEEL
sdss_lvmieb-0.5.3.dist-info/entry_points.txt
sdss_lvmieb-0.5.3.dist-info/RECORD
