Metadata-Version: 2.1
Name: sdss-lvmieb
Version: 0.5.3
Summary: Control software for the Local Volume Mapper Instrument Electronics Box
Home-page: https://github.com/sdss/lvmieb
License: BSD-3-Clause
Keywords: astronomy,software
Author: Changgon Kim
Author-email: changgonkim@khu.ac.kr
Maintainer: José Sánchez-Gallego
Maintainer-email: gallegoj@uw.edu
Requires-Python: >=3.9,<3.13
Classifier: Intended Audience :: Science/Research
Classifier: License :: OSI Approved :: BSD License
Classifier: Natural Language :: English
Classifier: Operating System :: OS Independent
Classifier: Programming Language :: Python :: 3
Classifier: Programming Language :: Python :: 3.9
Classifier: Programming Language :: Python :: 3.10
Classifier: Programming Language :: Python :: 3.11
Classifier: Programming Language :: Python :: 3.12
Classifier: Topic :: Documentation :: Sphinx
Classifier: Topic :: Software Development :: Libraries :: Python Modules
Requires-Dist: numpy (>=1.20.3,<2.0.0)
Requires-Dist: sdss-clu (>=2.0.0,<3.0.0)
Requires-Dist: sdss-drift (>=1.1.0,<2.0.0)
Requires-Dist: sdsstools (>=1.0.0,<2.0.0)
Project-URL: Documentation, https://sdss-lvmieb.readthedocs.org
Project-URL: Repository, https://github.com/sdss/lvmieb
